AUTHORS.rst
CONTRIBUTING.rst
HISTORY.rst
LICENSE
MANIFEST.in
README.rst
setup.py
django_resort.egg-info/PKG-INFO
django_resort.egg-info/SOURCES.txt
django_resort.egg-info/dependency_links.txt
django_resort.egg-info/not-zip-safe
django_resort.egg-info/top_level.txt
resort/__init__.py
resort/models.py
resort/static/js/resort.js
resort/templates/resort/base.html
resort/templates/resort/sort_link_frag.html
resort/templatetags/__init__.py
resort/templatetags/resort.py