Metadata-Version: 1.0
Name: django-resort
Version: 0.1.0
Summary: Implement sorting for ListView columns without changing your views.
Home-page: https://github.com/alixedi/django_resort
Author: Ali Zaidi
Author-email: alixedi@gmail.com
License: BSD
Keywords: django_resort
Platform: UNKNOWN
Classifier: Development Status :: 2 - Pre-Alpha
Classifier: Framework :: Django
Classifier: Intended Audience :: Developers
Classifier: License :: OSI Approved :: BSD License
Classifier: Natural Language :: English
Classifier: Programming Language :: Python :: 2
Classifier: Programming Language :: Python :: 2.6
Classifier: Programming Language :: Python :: 2.7
Classifier: Programming Language :: Python :: 3
Classifier: Programming Language :: Python :: 3.3
